elasticbatch/__init__.py
elasticbatch/buffer.py
elasticbatch/exceptions.py
elasticbatch/types.py
tests/__init__.py
tests/test_buffer.py
tests/test_exceptions.py
elasticbatch-1.0.0.dist-info/LICENSE
elasticbatch-1.0.0.dist-info/METADATA
elasticbatch-1.0.0.dist-info/WHEEL
elasticbatch-1.0.0.dist-info/top_level.txt
elasticbatch-1.0.0.dist-info/RECORD
