Metadata-Version: 2.1
Name: elasticbatch
Version: 1.0.0
Summary: Elasticsearch buffer for collecting and batch inserting Python data and pandas DataFrames
Home-page: https://github.com/dkaslovsky/ElasticBatch
Author: Daniel Kaslovsky
Author-email: dkaslovsky@gmail.com
License: MIT
Keywords: elasticsearch,python,pandas,dataframes,batch-processing
Platform: UNKNOWN
Classifier: Environment :: Console
Classifier: License :: OSI Approved :: MIT License
Classifier: Natural Language :: English
Classifier: Operating System :: OS Independent
Classifier: Programming Language :: Python :: 3.6
Classifier: Programming Language :: Python :: 3.7
Requires-Dist: elasticsearch
Provides-Extra: pandas
Requires-Dist: pandas ; extra == 'pandas'
